mktxp/__init__.py
mktxp/cli/__init__.py
mktxp/cli/dispatch.py
mktxp/cli/options.py
mktxp/cli/checks/__init__.py
mktxp/cli/checks/chk_pv.py
mktxp/cli/config/__init__.py
mktxp/cli/config/_mktxp.conf
mktxp/cli/config/config.py
mktxp/cli/config/mktxp.conf
mktxp/cli/output/__init__.py
mktxp/cli/output/address_list_out.py
mktxp/cli/output/capsman_out.py
mktxp/cli/output/conn_stats_out.py
mktxp/cli/output/dhcp_out.py
mktxp/cli/output/kid_control_out.py
mktxp/cli/output/netwatch_out.py
mktxp/cli/output/wifi_out.py
mktxp/collector/__init__.py
mktxp/collector/address_list_collector.py
mktxp/collector/bandwidth_collector.py
mktxp/collector/base_collector.py
mktxp/collector/bfd_collector.py
mktxp/collector/bgp_collector.py
mktxp/collector/capsman_collector.py
mktxp/collector/certificate_collector.py
mktxp/collector/connection_collector.py
mktxp/collector/container_collector.py
mktxp/collector/dhcp_collector.py
mktxp/collector/dns_collector.py
mktxp/collector/eoip_collector.py
mktxp/collector/firewall_collector.py
mktxp/collector/gre_collector.py
mktxp/collector/health_collector.py
mktxp/collector/identity_collector.py
mktxp/collector/interface_collector.py
mktxp/collector/ipip_collector.py
mktxp/collector/ipsec_collector.py
mktxp/collector/kid_control_device_collector.py
mktxp/collector/lte_collector.py
mktxp/collector/mktxp_collector.py
mktxp/collector/monitor_collector.py
mktxp/collector/neighbor_collector.py
mktxp/collector/netwatch_collector.py
mktxp/collector/package_collector.py
mktxp/collector/poe_collector.py
mktxp/collector/pool_collector.py
mktxp/collector/public_ip_collector.py
mktxp/collector/queue_collector.py
mktxp/collector/resource_collector.py
mktxp/collector/route_collector.py
mktxp/collector/routing_stats_collector.py
mktxp/collector/switch_collector.py
mktxp/collector/user_collector.py
mktxp/collector/w60g_collector.py
mktxp/collector/wlan_collector.py
mktxp/datasource/__init__.py
mktxp/datasource/address_list_ds.py
mktxp/datasource/base_ds.py
mktxp-1.2.15.dist-info/licenses/LICENSE
mktxp-1.2.15.dist-info/METADATA
mktxp-1.2.15.dist-info/WHEEL
mktxp-1.2.15.dist-info/entry_points.txt
mktxp-1.2.15.dist-info/top_level.txt
mktxp-1.2.15.dist-info/zip-safe
mktxp-1.2.15.dist-info/RECORD
