Metadata-Version: 2.4
Name: mktxp
Version: 1.2.15
Summary: Prometheus Exporter for Mikrotik RouterOS devices
Home-page: https://github.com/akpw/mktxp
Author: Arseniy Kuznetsov
Author-email: k.arseniy@gmail.com
License: GNU General Public License v2 (GPLv2)
Keywords: Mikrotik RouterOS Prometheus Exporter
Classifier: Development Status :: 4 - Beta
Classifier: License :: OSI Approved :: GNU General Public License v2 or later (GPLv2+)
Classifier: Programming Language :: Python
Classifier: Programming Language :: Python :: 3.8
Classifier: Programming Language :: Python :: 3 :: Only
Classifier: Intended Audience :: Developers
Classifier: Intended Audience :: System Administrators
Classifier: Intended Audience :: Information Technology
Classifier: Intended Audience :: Customer Service
Classifier: Operating System :: MacOS
Classifier: Operating System :: POSIX :: BSD :: FreeBSD
Classifier: Operating System :: POSIX :: Linux
Classifier: Topic :: System
Classifier: Topic :: System :: Systems Administration
Classifier: Topic :: Utilities
License-File: LICENSE
Requires-Dist: prometheus-client>=0.9.0
Requires-Dist: RouterOS-api>=0.19.0
Requires-Dist: configobj>=5.0.6
Requires-Dist: humanize>=3.2.0
Requires-Dist: texttable>=1.6.3
Requires-Dist: speedtest-cli>=2.1.2
Requires-Dist: waitress>=3.0.0
Requires-Dist: packaging>=24.0
Requires-Dist: pyyaml>=5.1
Provides-Extra: test
Requires-Dist: pytest; extra == "test"
Requires-Dist: pytest-mock; extra == "test"
Dynamic: author
Dynamic: author-email
Dynamic: classifier
Dynamic: description
Dynamic: description-content-type
Dynamic: home-page
Dynamic: keywords
Dynamic: license
Dynamic: license-file
Dynamic: provides-extra
Dynamic: requires-dist
Dynamic: summary
